evovaq/BigBangBigCrunch.py
evovaq/CHCAlgorithm.py
evovaq/DifferentialEvolution.py
evovaq/GeneticAlgorithm.py
evovaq/HillClimbing.py
evovaq/MemeticAlgorithm.py
evovaq/ParticleSwarmOptimization.py
evovaq/__init__.py
evovaq/problem.py
evovaq/tools/__init__.py
evovaq/tools/distances.py
evovaq/tools/operators.py
evovaq/tools/support.py
evovaq/tools/utils.py
evovaq-1.1.3.dist-info/licenses/LICENSE
evovaq-1.1.3.dist-info/METADATA
evovaq-1.1.3.dist-info/WHEEL
evovaq-1.1.3.dist-info/top_level.txt
evovaq-1.1.3.dist-info/RECORD
