Metadata-Version: 2.4
Name: evovaq
Version: 1.1.3
Summary: EVOlutionary algorithms toolbox for VAriational Quantum circuits
Home-page: https://github.com/Quasar-UniNA/EVOVAQ
Author: Angela Chiatto
Author-email: angela.chiatto@unina.it
License: MIT
Keywords: Quantum Computing,Evolutionary Algorithms,Variational Quantum Circuits
Classifier: Development Status :: 3 - Alpha
Classifier: Intended Audience :: Developers
Classifier: Topic :: Software Development :: Build Tools
Classifier: License :: OSI Approved :: MIT License
Classifier: Programming Language :: Python :: 3
License-File: LICENSE
Requires-Dist: numpy>=1.23.5
Requires-Dist: tabulate==0.8.10
Requires-Dist: tqdm==4.64.1
Requires-Dist: matplotlib>=3.5.1
Requires-Dist: pandas>=1.4.2
Requires-Dist: openpyxl==3.0.9
Dynamic: author
Dynamic: author-email
Dynamic: classifier
Dynamic: description
Dynamic: description-content-type
Dynamic: home-page
Dynamic: keywords
Dynamic: license
Dynamic: license-file
Dynamic: requires-dist
Dynamic: summary
